jsua/__init__.py
jsua/reader.py
jsua/parser.py
jsua-0.0.2.dist-info/METADATA
jsua-0.0.2.dist-info/DESCRIPTION.rst
jsua-0.0.2.dist-info/metadata.json
jsua-0.0.2.dist-info/WHEEL
jsua-0.0.2.dist-info/entry_points.txt
jsua-0.0.2.dist-info/top_level.txt
jsua-0.0.2.dist-info/RECORD
