Metadata-Version: 2.0
Name: jsua
Version: 0.0.2
Summary: A parser for JSON that can start at an arbitrary point in the file
Home-page: https://github.com/tecywiz121/jsua
Author: Sam Wilson
Author-email: sam@binarycake.ca
License: LGPL
Platform: UNKNOWN
Classifier: Development Status :: 3 - Alpha
Classifier: Intended Audience :: Developers
Classifier: Programming Language :: Python :: 3
Classifier: License :: OSI Approved :: GNU Lesser General Public License v3 or later (LGPLv3+)
